stormshield_bouncer/__init__.py
stormshield_bouncer/main.py
stormshield_bouncer/utils.py
crowdsec_stormshield_bouncer-0.0.1.dist-info/LICENSE
crowdsec_stormshield_bouncer-0.0.1.dist-info/METADATA
crowdsec_stormshield_bouncer-0.0.1.dist-info/WHEEL
crowdsec_stormshield_bouncer-0.0.1.dist-info/entry_points.txt
crowdsec_stormshield_bouncer-0.0.1.dist-info/top_level.txt
crowdsec_stormshield_bouncer-0.0.1.dist-info/RECORD
