Metadata-Version: 2.1
Name: crowdsec-stormshield-bouncer
Version: 0.0.1
Summary: CrowdSec Stormshield Bouncer
Home-page: https://github.com/crowdsecurity/crowdsec-stormshield-bouncer
Author: CrowdSec
Author-email: core.tech@crowdsec.net
Project-URL: Bug Tracker, https://github.com/crowdsecurity/crowdsec-stormshield-bouncer/issues
Classifier: Programming Language :: Python :: 3
Classifier: License :: OSI Approved :: MIT License
Classifier: Operating System :: OS Independent
Requires-Python: >=3.7
License-File: LICENSE
Requires-Dist: urllib3 ==1.26.16
Requires-Dist: pyyaml
Requires-Dist: stormshield.sns.sslclient
Requires-Dist: scp
Requires-Dist: pycrowdsec ==0.0.5
Requires-Dist: paramiko
Requires-Dist: pytimeparse
